LICENSE
lovecraft/__init__.py
lovecraft/caches/disk_cache.py
lovecraft/cli.py
lovecraft/input/__init__.py
lovecraft/input/letters.py
lovecraft/input/stories.py
lovecraft-0.1.1.dist-info/LICENSE
lovecraft-0.1.1.dist-info/METADATA
lovecraft-0.1.1.dist-info/WHEEL
lovecraft-0.1.1.dist-info/RECORD
